discord_musicbot-0.0.3.dev20170604.dist-info/DESCRIPTION.rst
discord_musicbot-0.0.3.dev20170604.dist-info/METADATA
discord_musicbot-0.0.3.dev20170604.dist-info/RECORD
discord_musicbot-0.0.3.dev20170604.dist-info/WHEEL
discord_musicbot-0.0.3.dev20170604.dist-info/metadata.json
discord_musicbot-0.0.3.dev20170604.dist-info/top_level.txt
musicbot/__init__.py
musicbot/__main__.py
musicbot/apis.py
musicbot/bot.py
musicbot/bot_functions.py
musicbot/conf.py
musicbot/settings.py
