Metadata-Version: 2.0
Name: discord-musicbot
Version: 0.0.3.dev20170604
Summary: MusicBot bot for Discord.
Home-page: https://github.com/andasilva/MusicBot
Author: Quentin Vaucher de la Croix & Neto da Silva André
Author-email: quentin.vaucher@he-arc.ch & andre.netodasilva@he-arc.ch
License: https://opensource.org/licenses/BSD-3-Clause
Keywords: discord asyncio bot
Platform: UNKNOWN
Classifier: Development Status :: 3 - Alpha
Classifier: Environment :: Console
Classifier: Intended Audience :: Education
Classifier: Operating System :: MacOS :: MacOS X
Classifier: Operating System :: Microsoft :: Windows
Classifier: Operating System :: POSIX
Classifier: Programming Language :: Python :: 3 :: Only
Classifier: Programming Language :: Python :: 3.6
Classifier: Programming Language :: Python :: Implementation :: CPython
Classifier: Topic :: Multimedia :: Sound/Audio
Requires-Python: >=3.6
Requires-Dist: aiohttp (>=2.1.0)
Requires-Dist: selenium (==3.4.3)
Requires-Dist: spotipy (>=2.4.4)
Provides-Extra: docs
Requires-Dist: Sphinx (>=1.6.0); extra == 'docs'
Requires-Dist: sphinxcontrib-trio; extra == 'docs'
Provides-Extra: fast
Requires-Dist: aiodns; extra == 'fast'
Requires-Dist: cchardet; extra == 'fast'
Provides-Extra: qa
Requires-Dist: flake8; extra == 'qa'
Requires-Dist: isort; extra == 'qa'
Requires-Dist: pycodestyle; extra == 'qa'
Requires-Dist: pydocstyle; extra == 'qa'
Requires-Dist: rstcheck; extra == 'qa'
